ReFrame/__init__.py
ReFrame/background_remover.py
ReFrame/cli.py
ReFrame/extract_frames.py
ReFrame/gif_creator.py
ReFrame/image_converter.py
ReFrame/image_resizer.py
ReFrame/utils.py
reframe_cli-1.2.0.dist-info/METADATA
reframe_cli-1.2.0.dist-info/WHEEL
reframe_cli-1.2.0.dist-info/entry_points.txt
reframe_cli-1.2.0.dist-info/top_level.txt
reframe_cli-1.2.0.dist-info/RECORD
