Metadata-Version: 2.4
Name: reframe-cli
Version: 1.2.0
Summary: ReFrame-CLI is a Python-based command-line tool to streamline your video and image manipulation tasks. Ideal for preparing image datasets for training machine learning models, including generative AI and diffusion models. Can handle videos of any length.
Author: Gour4v
Author-email: chatgai.note@gmail.com
License: MIT
Project-URL: GitHub, https://github.com/ForgeL4bs/ReFrame
Project-URL: Documentation, https://github.com/ForgeL4bs/ReFrame#readme
Project-URL: Issue Tracker, https://github.com/ForgeL4bs/ReFrame/issues
Classifier: Programming Language :: Python :: 3
Classifier: Operating System :: OS Independent
Requires-Python: >=3.7
Requires-Dist: opencv-python
Requires-Dist: pillow
Requires-Dist: imageio
Requires-Dist: pillow-heif
Requires-Dist: tqdm
Requires-Dist: rembg
Requires-Dist: onnxruntime
Dynamic: author
Dynamic: author-email
Dynamic: classifier
Dynamic: description
Dynamic: description-content-type
Dynamic: license
Dynamic: project-url
Dynamic: requires-dist
Dynamic: requires-python
Dynamic: summary
